pymmcore_plus/__init__.py
pymmcore_plus/_accumulator.py
pymmcore_plus/_benchmark.py
pymmcore_plus/_build.py
pymmcore_plus/_cli.py
pymmcore_plus/_discovery.py
pymmcore_plus/_ipy_completion.py
pymmcore_plus/_logger.py
pymmcore_plus/_pymmcore.py
pymmcore_plus/_util.py
pymmcore_plus/install.py
pymmcore_plus/mocks.py
pymmcore_plus/py.typed
pymmcore_plus/seq_tester.py
pymmcore_plus/core/__init__.py
pymmcore_plus/core/_adapter.py
pymmcore_plus/core/_config.py
pymmcore_plus/core/_config_group.py
pymmcore_plus/core/_constants.py
pymmcore_plus/core/_device.py
pymmcore_plus/core/_metadata.py
pymmcore_plus/core/_mmcore_plus.py
pymmcore_plus/core/_property.py
pymmcore_plus/core/_sequencing.py
pymmcore_plus/core/events/__init__.py
pymmcore_plus/core/events/_deprecated.py
pymmcore_plus/core/events/_device_signal_view.py
pymmcore_plus/core/events/_norm_slot.py
pymmcore_plus/core/events/_prop_event_mixin.py
pymmcore_plus/core/events/_protocol.py
pymmcore_plus/core/events/_psygnal.py
pymmcore_plus/core/events/_qsignals.py
pymmcore_plus/experimental/__init__.py
pymmcore_plus/experimental/simulate/__init__.py
pymmcore_plus/experimental/simulate/_objects.py
pymmcore_plus/experimental/simulate/_render.py
pymmcore_plus/experimental/simulate/_sample.py
pymmcore_plus/experimental/unicore/__init__.py
pymmcore_plus/experimental/unicore/_device_manager.py
pymmcore_plus/experimental/unicore/_proxy.py
pymmcore_plus/experimental/unicore/core/__init__.py
pymmcore_plus/experimental/unicore/core/_config.py
pymmcore_plus/experimental/unicore/core/_sequence_buffer.py
pymmcore_plus/experimental/unicore/core/_unicore.py
pymmcore_plus/experimental/unicore/devices/__init__.py
pymmcore_plus/experimental/unicore/devices/_camera.py
pymmcore_plus/experimental/unicore/devices/_device_base.py
pymmcore_plus/experimental/unicore/devices/_generic_device.py
pymmcore_plus/experimental/unicore/devices/_hub.py
pymmcore_plus/experimental/unicore/devices/_properties.py
pymmcore_plus-0.17.0.dist-info/METADATA
pymmcore_plus-0.17.0.dist-info/WHEEL
pymmcore_plus-0.17.0.dist-info/entry_points.txt
pymmcore_plus-0.17.0.dist-info/licenses/LICENSE
pymmcore_plus-0.17.0.dist-info/RECORD
