Metadata-Version: 2.4
Name: pymmcore-plus
Version: 0.17.0
Summary: pymmcore superset providing improved APIs, event handling, and a pure python acquisition engine
Project-URL: Source, https://github.com/pymmcore-plus/pymmcore-plus
Project-URL: Tracker, https://github.com/pymmcore-plus/pymmcore-plus/issues
Project-URL: Documentation, https://pymmcore-plus.github.io/pymmcore-plus
Author-email: Talley Lambert <talley.lambert@gmail.com>, Federico Gasparoli <federico.gasparoli@gmail.com>, Ian Hunt-Isaak <ianhuntisaak@gmail.com>
License: BSD 3-Clause License
License-File: LICENSE
Keywords: micro-manager,microscope,smart-microscopy
Classifier: Development Status :: 4 - Beta
Classifier: Intended Audience :: Developers
Classifier: Intended Audience :: Science/Research
Classifier: License :: OSI Approved :: BSD License
Classifier: Operating System :: OS Independent
Classifier: Programming Language :: Python
Classifier: Programming Language :: Python :: 3
Classifier: Programming Language :: Python :: 3.9
Classifier: Programming Language :: Python :: 3.10
Classifier: Programming Language :: Python :: 3.11
Classifier: Programming Language :: Python :: 3.12
Classifier: Programming Language :: Python :: 3.13
Classifier: Topic :: System :: Hardware
Classifier: Topic :: System :: Hardware :: Hardware Drivers
Classifier: Topic :: Utilities
Requires-Python: >=3.9
Requires-Dist: numpy>=1.25.2
Requires-Dist: numpy>=1.26.0; python_version >= '3.12'
Requires-Dist: numpy>=2.1.0; python_version >= '3.13'
Requires-Dist: ome-types>=0.6.0
Requires-Dist: platformdirs>=3.0.0
Requires-Dist: psygnal>=0.10
Requires-Dist: pymmcore>=11.10.0.74.0
Requires-Dist: rich>=10.2.0
Requires-Dist: tensorstore!=0.1.72,>=0.1.67
Requires-Dist: tensorstore!=0.1.72,>=0.1.71; python_version >= '3.13'
Requires-Dist: typer>=0.13.0
Requires-Dist: typing-extensions>=4
Requires-Dist: useq-schema>=0.7.2
Provides-Extra: cli
Requires-Dist: rich>=10.2.0; extra == 'cli'
Requires-Dist: typer>=0.13.0; extra == 'cli'
Provides-Extra: io
Requires-Dist: tifffile>=2021.6.14; extra == 'io'
Requires-Dist: zarr<3,>=2.15; extra == 'io'
Provides-Extra: pyqt5
Requires-Dist: pyqt5>=5.15.4; extra == 'pyqt5'
Provides-Extra: pyqt6
Requires-Dist: pyqt6>=6.4.2; extra == 'pyqt6'
Provides-Extra: pyside2
Requires-Dist: pyside2>=5.15.2.1; extra == 'pyside2'
Provides-Extra: pyside6
Requires-Dist: pyside6==6.7.3; extra == 'pyside6'
Provides-Extra: simulate
Requires-Dist: pillow>=11.0; extra == 'simulate'
